orchestapicli/__init__.py
orchestapicli/_version.py
orchestapicli/cli.py
orchestapicli/cmds.py
orchestapicli/core.py
ttoa_cli-0.0.1.dist-info/LICENSE
ttoa_cli-0.0.1.dist-info/METADATA
ttoa_cli-0.0.1.dist-info/WHEEL
ttoa_cli-0.0.1.dist-info/entry_points.txt
ttoa_cli-0.0.1.dist-info/top_level.txt
ttoa_cli-0.0.1.dist-info/RECORD
