Metadata-Version: 2.1
Name: ttoa-cli
Version: 0.0.1
Summary: CLI for TTOA
Home-page: https://github.com/TapTarget/TTO
Author: Rick Lamers
Author-email: rick@orchest.io
License: Apache 2.0
Project-URL: Documentation, https://docs.orchest.io/en/stable/
Project-URL: Source Code, https://github.com/TapTarget/TTO/tree/master/orchest-cli
Keywords: TTOA
Platform: UNKNOWN
Classifier: Development Status :: 4 - Beta
Classifier: Environment :: Console
Classifier: Intended Audience :: Developers
Classifier: Intended Audience :: Science/Research
Classifier: Intended Audience :: System Administrators
Classifier: License :: OSI Approved :: Apache Software License
Classifier: Topic :: Utilities
Requires-Python: >=3.8
Requires-Dist: click >=8.0.0
Requires-Dist: requests
